paralex/__init__.py
paralex/datasets.py
paralex/explorer.py
paralex/gendoc.py
paralex/main.py
paralex/markdown.py
paralex/meta.py
paralex/paths.py
paralex/strategies.py
paralex/utils.py
paralex/validate.py
paralex/docs/advanced-metadata.md
paralex/docs/changelog.md
paralex/docs/datasets.md
paralex/docs/dear.md
paralex/docs/examples.md
paralex/docs/fair-care.md
paralex/docs/faq.md
paralex/docs/graph-paralex.png
paralex/docs/index.md
paralex/docs/index.md.orig
paralex/docs/known-datasets.csv
paralex/docs/language_stats.csv
paralex/docs/long-form.md
paralex/docs/mapframe.html
paralex/docs/metadata.md
paralex/docs/notes.md
paralex/docs/owl2html.xsl
paralex/docs/paralex.png
paralex/docs/paralex_blk.png
paralex/docs/paralex_ontology.xml
paralex/docs/principles.md
paralex/docs/result.geojson
paralex/docs/sounds.md
paralex/docs/sources.md
paralex/docs/specs.md
paralex/docs/specs.md.orig
paralex/docs/specs.pdf
paralex/docs/specs.tex
paralex/docs/standard.md
paralex/docs/structure-paradigms.md
paralex/docs/tutorial.md
paralex/docs/css/extra.css
paralex/standard/columns_spec.json
paralex/standard/data_sheet.md
paralex/standard/files_spec.json
paralex/standard/package_spec.json
paralex/standard/paralex.package.json
paralex/standard/paralex.package.json.orig
paralex/standard/tables_spec.json
paralex/templates/__init__.py
paralex/templates/field.md
paralex/templates/package.md
paralex/templates/resource.md
paralex-2.2.16.dist-info/METADATA
paralex-2.2.16.dist-info/WHEEL
paralex-2.2.16.dist-info/entry_points.txt
paralex-2.2.16.dist-info/top_level.txt
paralex-2.2.16.dist-info/RECORD
