Metadata-Version: 2.1
Name: paralex
Version: 2.2.16
Summary: Standard for lexicons of inflected paradigms
Author: Sacha Beniamine
Classifier: Operating System :: OS Independent
Classifier: Programming Language :: Python :: 3
Classifier: Topic :: Software Development :: Libraries
Requires-Python: >=3.9
Requires-Dist: pandas >=2.0.3
Requires-Dist: frictionless >=5.18.0
Requires-Dist: colorama
Requires-Dist: python-slugify
Requires-Dist: hypothesis
Requires-Dist: python-iso639
Requires-Dist: pybtex
Requires-Dist: seaborn
Requires-Dist: tqdm
Provides-Extra: docs
Requires-Dist: mkdocs >=1.1.2 ; extra == 'docs'
Requires-Dist: mkdocs-material ; extra == 'docs'
Requires-Dist: mkdocs-include-markdown-plugin ; extra == 'docs'
Requires-Dist: mkdocs-table-reader-plugin ; extra == 'docs'
